pipoe/__init__.py
pipoe/licenses.py
pipoe/pipoe.py
pipoe-2019.11.dist-info/COPYING
pipoe-2019.11.dist-info/METADATA
pipoe-2019.11.dist-info/WHEEL
pipoe-2019.11.dist-info/entry_points.txt
pipoe-2019.11.dist-info/top_level.txt
pipoe-2019.11.dist-info/RECORD
