Metadata-Version: 2.1
Name: pipoe
Version: 2019.11
Summary: Generate python bitbake recipes from pypi metadata.
Home-page: https://github.com/NFJones/pipoe
Author: Neil F Jones
License: UNKNOWN
Keywords: yocto bitbake openembedded
Platform: UNKNOWN
Classifier: Intended Audience :: Developers
Classifier: Topic :: Software Development :: Build Tools
Classifier: License :: OSI Approved :: MIT License
Classifier: Programming Language :: Python :: 3
Requires-Python: !=3.0.*, !=3.1.*, !=3.2.*, !=3.3.*, <4
Requires-Dist: Parsley (==1.3)
Requires-Dist: pep508-parser (==2019.3)
Requires-Dist: pkginfo (==1.5.0.1)
